rebelai/__init__.py
rebelai/const.py
rebelai/enums.py
rebelai/py.typed
rebelai/ai/__init__.py
rebelai/ai/alpaca.py
rebelai/ai/deepai.py
rebelai/ai/deepl.py
rebelai/ai/gpt.py
rebelai/ai/h2o.py
rebelai/ai/inferkit.py
rebelai/ai/pollinations.py
rebelai/ai/prodia.py
rebelai/ai/py.typed
rebelai-4.1.0.dist-info/LICENSE
rebelai-4.1.0.dist-info/METADATA
rebelai-4.1.0.dist-info/WHEEL
rebelai-4.1.0.dist-info/top_level.txt
rebelai-4.1.0.dist-info/zip-safe
rebelai-4.1.0.dist-info/RECORD
