Metadata-Version: 2.1
Name: rebelai
Version: 4.1.0
Summary: providing free access to proprietary ai models in python
Home-page: https://ari-web.xyz/gh/rebelai
Author: Ari Archer
Author-email: ari.web.xyz@gmail.com
License: GPLv3+
Keywords: alpaca,deepai,deepl,gpt,openai,inferkit,pollinations,prodia,free,ai,machine learning,free ai,api,async,aiohttp
Classifier: Development Status :: 5 - Production/Stable
Classifier: Intended Audience :: Developers
Classifier: License :: OSI Approved :: GNU General Public License v3 or later (GPLv3+)
Classifier: Operating System :: OS Independent
Classifier: Programming Language :: Python :: 3
Classifier: Programming Language :: Python :: 3.9
Classifier: Programming Language :: Python :: 3.10
Classifier: Programming Language :: Python :: 3.11
Classifier: Programming Language :: Python :: 3.12
Classifier: Topic :: Internet :: WWW/HTTP
Classifier: Topic :: Software Development :: Libraries :: Python Modules
Classifier: Typing :: Typed
License-File: LICENSE
Requires-Dist: aiohttp
